soifunc/__init__.py
soifunc/deband.py
soifunc/denoise.py
soifunc/interpolate.py
soifunc/py.typed
soifunc/resize.py
soifunc-0.12.0.dist-info/LICENSE
soifunc-0.12.0.dist-info/METADATA
soifunc-0.12.0.dist-info/WHEEL
soifunc-0.12.0.dist-info/RECORD
