Metadata-Version: 2.3
Name: soifunc
Version: 0.12.0
Summary: Soichiro's VapourSynth Functions Collection
License: MIT
Author: Josh Holmer
Author-email: jholmer.in@gmail.com
Requires-Python: >=3.12,<4.0
Classifier: License :: OSI Approved :: MIT License
Classifier: Programming Language :: Python :: 3
Classifier: Programming Language :: Python :: 3.12
Classifier: Programming Language :: Python :: 3.13
Requires-Dist: vapoursynth (>=68)
Requires-Dist: vsjetpack (>=0.7.1,<0.8.0)
